{
    "State.fddd4bc2-5bcb-4352-98d6-07b326e40e3d": {
        "id": "fddd4bc2-5bcb-4352-98d6-07b326e40e3d",
        "created_at": "2021-12-21T15:30:13.856504",
        "updated_at": "2021-12-21T15:30:13.856509",
        "name": "California",
        "__class__": "State"
    },
    "State.a41c649c-bcc3-4ab3-84e0-8704555aae38": {
        "id": "a41c649c-bcc3-4ab3-84e0-8704555aae38",
        "created_at": "2021-12-21T15:30:13.856870",
        "updated_at": "2021-12-21T15:30:13.856873",
        "name": "Arizona",
        "__class__": "State"
    },
    "Place.055ce55e-2ae8-4315-bf1d-6d2ed3fd66d3": {
        "id": "055ce55e-2ae8-4315-bf1d-6d2ed3fd66d3",
        "created_at": "2021-12-21T15:30:13.857513",
        "updated_at": "2021-12-21T15:30:13.857516",
        "city_id": "0001",
        "user_id": "0001",
        "name": "My little house",
        "number_rooms": 4,
        "number_bathrooms": 2,
        "max_guest": 10,
        "price_by_night": 300,
        "latitude": 37.773972,
        "longitude": -122.431297,
        "__class__": "Place"
    }
}